{
  "desktop": [
    {
      "name": "Chendito",
      "image": "default.svg", 
      "id": 1
    },
    {
      "name": "Developer", 
      "image": "default.svg", 
      "id": 2
    },
    {
      "name": "JavaScript", 
      "image": "default.svg", 
      "id": 3
    },
    {
      "name": "ChatBot", 
      "image": "default.svg", 
      "id": 4
    },
    {
      "name": "Chendo.io", 
      "image": "default.svg", 
      "id": 5
    },
    {
      "name": "Captures", 
      "image": "default.svg", 
      "id": 6
    }
  ],
  "documents": [
    {
      "name": "Hacking", 
      "image": "default.svg", 
      "id": 1
    },
    {
      "name": "History JavaScript", 
      "image": "default.svg", 
      "id": 2
    },
    {
      "name": "Php Master", 
      "image": "default.svg", 
      "id": 3
    },
    {
      "name": "Json Master", 
      "image": "default.svg", 
      "id": 4
    },
    {
      "name": "Node Master", 
      "image": "default.svg", 
      "id": 5
    },
    {
      "name": "React Master", 
      "image": "default.svg", 
      "id": 6
    },
    {
      "name": "Development", 
      "image": "default.svg", 
      "id": 7
    }
  ],
  "downloads": [
    {
      "name": "Text Lorem ipsum", 
      "image": "default.svg", 
      "id": 1
    },
    {
      "name": "Math Fisc Science", 
      "image": "default.svg", 
      "id": 2
    },
    {
      "name": "Music Hack", 
      "image": "default.svg", 
      "id": 3
    },
    {
      "name": "Entertainment", 
      "image": "default.svg", 
      "id": 4
    },
    {
      "name": "Source Code", 
      "image": "default.svg", 
      "id": 5
    },
    {
      "name": "Full Stack", 
      "image": "default.svg", 
      "id": 6
    },
    {
      "name": "React Hooks", 
      "image": "default.svg", 
      "id": 7
    }
  ],
  "music": [
    {
      "name": "I will be rain - Bruno Mars | Cover", 
      "image": "doc_music.svg", 
      "album": "bruno-mars.jpg",
      "mp3": "it-will-rain.mp3",
      "id": 1
    },
    {
      "name": "More than words - Extreme", 
      "image": "doc_music.svg", 
      "album": "extreme.jpg",
      "mp3": "more-than-words.mp3",
      "id": 2
    },
    {
      "name": "Let it be - The Beatles | Cover", 
      "image": "doc_music.svg", 
      "album": "the-beatles.jpg",
      "mp3": "let-it-be.mp3",
      "id": 3
    },
    {
      "name": "Foreigner I want to...", 
      "image": "doc_music.svg", 
      "album": "foreigner.jpg",
      "mp3": "i-want-to.mp3",
      "id": 4
    },
    {
      "name": "Tears in heaven - Boyce A. | Cover", 
      "image": "doc_music.svg", 
      "album": "boyce-avenue.jpg",
      "mp3": "tears-in-heaven.mp3",
      "id": 5
    },
    {
      "name": "Bee Gees - How deep is your love", 
      "image": "doc_music.svg", 
      "album": "bee-gees.jpg",
      "mp3": "how-deep-is-your-love.mp3",
      "id": 6
    },
    {
      "name": "Crazy | AeroSmith", 
      "image": "doc_music.svg", 
      "album": "aerosmith.jpg",
      "mp3": "crazy.mp3",
      "id": 7
    }
  ],
  "pictures": [
    {
      "name": "bruno-mars", 
      "image": "doc_image.svg",
      "id": 1
    },
    {
      "name": "extreme", 
      "image": "doc_image.svg",
      "id": 2
    },
    {
      "name": "the-beatles", 
      "image": "doc_image.svg",
      "id": 3
    },
    {
      "name": "foreigner", 
      "image": "doc_image.svg",
      "id": 4
    },
    {
      "name": "boyce-avenue", 
      "image": "doc_image.svg",
      "id": 5
    },
    {
      "name": "bee-gees", 
      "image": "doc_image.svg",
      "id": 6
    },
    {
      "name": "aerosmith", 
      "image": "doc_image.svg",
      "id": 7
    }
  ],
  "videos": [
    {
      "name": "The Store Die", 
      "image": "doc_video.svg",
      "id": 1
    },
    {
      "name": "Single Page Features", 
      "image": "doc_video.svg",
      "id": 2
    }
  ]
}